{
  "chunk_id": 1,
  "domain": "clio",
  "date": "2026-03-06",
  "timestamp": "2026-03-06T09:53:19.599317",
  "results": {
    "public": [
      {
        "url": "https://clio-tools.s3.eu-west-1.amazonaws.com",
        "bucket": "clio-tools",
        "region": "eu-west-1",
        "status": 200,
        "access": "public",
        "timestamp": "2026-03-06T07:31:56.189453"
      },
      {
        "url": "https://clio-al.s3.us-east-1.amazonaws.com",
        "bucket": "clio-al",
        "region": "us-east-1",
        "status": 200,
        "access": "public",
        "timestamp": "2026-03-06T07:51:27.373746"
      },
      {
        "url": "https://cliobuilds.s3.us-west-2.amazonaws.com",
        "bucket": "cliobuilds",
        "region": "us-west-2",
        "status": 200,
        "access": "public",
        "timestamp": "2026-03-06T08:22:49.298132"
      },
      {
        "url": "https://capstoneclio.s3.us-east-1.amazonaws.com",
        "bucket": "capstoneclio",
        "region": "us-east-1",
        "status": 200,
        "access": "public",
        "timestamp": "2026-03-06T08:26:46.178639"
      },
      {
        "url": "https://cliodata.s3.us-east-1.amazonaws.com",
        "bucket": "cliodata",
        "region": "us-east-1",
        "status": 200,
        "access": "public",
        "timestamp": "2026-03-06T08:35:52.901983"
      },
      {
        "url": "https://cliorepository.s3.us-east-2.amazonaws.com",
        "bucket": "cliorepository",
        "region": "us-east-2",
        "status": 200,
        "access": "public",
        "timestamp": "2026-03-06T09:10:57.800573"
      }
    ],
    "private": []
  },
  "stats": {
    "total_checked": 361323,
    "public_found": 6,
    "private_found": 0
  }
}