{
  "chunk_id": 1,
  "domain": "com",
  "date": "2026-02-25",
  "timestamp": "2026-02-25T23:08:29.497473",
  "providers": [
    "azure",
    "linode",
    "ibm",
    "digitalocean"
  ],
  "results": {
    "public": [
      {
        "url": "https://carlos-com.fra1.digitaloceanspaces.com",
        "bucket": "carlos-com",
        "provider": "digitalocean",
        "region": "fra1",
        "status": 200,
        "access": "public",
        "timestamp": "2026-02-25T22:25:23.316678"
      },
      {
        "url": "https://ecom.nyc3.digitaloceanspaces.com",
        "bucket": "ecom",
        "provider": "digitalocean",
        "region": "nyc3",
        "status": 200,
        "access": "public",
        "timestamp": "2026-02-25T22:26:02.131243"
      },
      {
        "url": "https://ncom.nyc3.digitaloceanspaces.com",
        "bucket": "ncom",
        "provider": "digitalocean",
        "region": "nyc3",
        "status": 200,
        "access": "public",
        "timestamp": "2026-02-25T22:27:53.269210"
      }
    ],
    "private": []
  },
  "stats": {
    "total_checked": 570510,
    "public_found": 3,
    "private_found": 0
  }
}