{
  "chunk_id": 1,
  "domain": "auto",
  "date": "2026-01-16",
  "timestamp": "2026-01-16T22:22:27.989788",
  "results": {
    "public": [
      {
        "url": "https://autoslots.s3.ap-southeast-1.amazonaws.com",
        "bucket": "autoslots",
        "region": "ap-southeast-1",
        "status": 200,
        "access": "public",
        "timestamp": "2026-01-16T19:26:42.879130"
      },
      {
        "url": "https://auto-media.s3.eu-west-1.amazonaws.com",
        "bucket": "auto-media",
        "region": "eu-west-1",
        "status": 200,
        "access": "public",
        "timestamp": "2026-01-16T19:27:35.572441"
      },
      {
        "url": "https://autoservices.s3.us-east-2.amazonaws.com",
        "bucket": "autoservices",
        "region": "us-east-2",
        "status": 200,
        "access": "public",
        "timestamp": "2026-01-16T19:35:40.056904"
      },
      {
        "url": "https://autoru.s3.eu-central-1.amazonaws.com",
        "bucket": "autoru",
        "region": "eu-central-1",
        "status": 200,
        "access": "public",
        "timestamp": "2026-01-16T19:36:34.681041"
      },
      {
        "url": "https://auto-events.s3.us-east-2.amazonaws.com",
        "bucket": "auto-events",
        "region": "us-east-2",
        "status": 200,
        "access": "public",
        "timestamp": "2026-01-16T19:42:25.168867"
      },
      {
        "url": "https://autokit.s3.eu-west-2.amazonaws.com",
        "bucket": "autokit",
        "region": "eu-west-2",
        "status": 200,
        "access": "public",
        "timestamp": "2026-01-16T19:46:41.691692"
      },
      {
        "url": "https://transfer-auto.s3.ap-southeast-1.amazonaws.com",
        "bucket": "transfer-auto",
        "region": "ap-southeast-1",
        "status": 200,
        "access": "public",
        "timestamp": "2026-01-16T19:47:43.539622"
      },
      {
        "url": "https://s3.eu-west-2.amazonaws.com/auto.works",
        "bucket": "auto.works",
        "region": "eu-west-2",
        "status": 200,
        "access": "public",
        "timestamp": "2026-01-16T19:51:45.493669"
      },
      {
        "url": "https://express-auto.s3.us-east-1.amazonaws.com",
        "bucket": "express-auto",
        "region": "us-east-1",
        "status": 200,
        "access": "public",
        "timestamp": "2026-01-16T19:52:09.673756"
      },
      {
        "url": "https://autoid.s3.us-west-1.amazonaws.com",
        "bucket": "autoid",
        "region": "us-west-1",
        "status": 200,
        "access": "public",
        "timestamp": "2026-01-16T19:57:15.037498"
      },
      {
        "url": "https://autosquare.s3.ap-south-1.amazonaws.com",
        "bucket": "autosquare",
        "region": "ap-south-1",
        "status": 200,
        "access": "public",
        "timestamp": "2026-01-16T20:02:54.011035"
      },
      {
        "url": "https://autologin.s3.eu-west-1.amazonaws.com",
        "bucket": "autologin",
        "region": "eu-west-1",
        "status": 200,
        "access": "public",
        "timestamp": "2026-01-16T20:04:23.427776"
      },
      {
        "url": "https://autof.s3.us-east-1.amazonaws.com",
        "bucket": "autof",
        "region": "us-east-1",
        "status": 200,
        "access": "public",
        "timestamp": "2026-01-16T20:10:01.376614"
      },
      {
        "url": "https://autowebinar.s3.ca-central-1.amazonaws.com",
        "bucket": "autowebinar",
        "region": "ca-central-1",
        "status": 200,
        "access": "public",
        "timestamp": "2026-01-16T20:11:13.738305"
      },
      {
        "url": "https://autoaffiliate.s3.us-east-2.amazonaws.com",
        "bucket": "autoaffiliate",
        "region": "us-east-2",
        "status": 200,
        "access": "public",
        "timestamp": "2026-01-16T20:12:20.424547"
      },
      {
        "url": "https://auto6.s3.us-east-1.amazonaws.com",
        "bucket": "auto6",
        "region": "us-east-1",
        "status": 200,
        "access": "public",
        "timestamp": "2026-01-16T20:15:25.114568"
      },
      {
        "url": "https://auto-exchange.s3.ap-southeast-2.amazonaws.com",
        "bucket": "auto-exchange",
        "region": "ap-southeast-2",
        "status": 200,
        "access": "public",
        "timestamp": "2026-01-16T20:24:30.207822"
      },
      {
        "url": "https://deploy-auto.s3.us-east-1.amazonaws.com",
        "bucket": "deploy-auto",
        "region": "us-east-1",
        "status": 200,
        "access": "public",
        "timestamp": "2026-01-16T20:25:44.608611"
      },
      {
        "url": "https://auto-dist.s3.eu-west-2.amazonaws.com",
        "bucket": "auto-dist",
        "region": "eu-west-2",
        "status": 200,
        "access": "public",
        "timestamp": "2026-01-16T20:28:39.727038"
      },
      {
        "url": "https://auto-4.s3.us-east-1.amazonaws.com",
        "bucket": "auto-4",
        "region": "us-east-1",
        "status": 200,
        "access": "public",
        "timestamp": "2026-01-16T20:30:09.391082"
      },
      {
        "url": "https://autosocial.s3.us-east-1.amazonaws.com",
        "bucket": "autosocial",
        "region": "us-east-1",
        "status": 200,
        "access": "public",
        "timestamp": "2026-01-16T20:42:02.972754"
      },
      {
        "url": "https://ecomauto.s3.us-west-1.amazonaws.com",
        "bucket": "ecomauto",
        "region": "us-west-1",
        "status": 200,
        "access": "public",
        "timestamp": "2026-01-16T20:45:58.047835"
      },
      {
        "url": "https://autobook.s3.eu-west-2.amazonaws.com",
        "bucket": "autobook",
        "region": "eu-west-2",
        "status": 200,
        "access": "public",
        "timestamp": "2026-01-16T20:50:18.170555"
      },
      {
        "url": "https://auto-checkout.s3.ap-northeast-1.amazonaws.com",
        "bucket": "auto-checkout",
        "region": "ap-northeast-1",
        "status": 200,
        "access": "public",
        "timestamp": "2026-01-16T20:55:16.450352"
      },
      {
        "url": "https://ec2auto.s3.us-west-1.amazonaws.com",
        "bucket": "ec2auto",
        "region": "us-west-1",
        "status": 200,
        "access": "public",
        "timestamp": "2026-01-16T21:02:57.571294"
      },
      {
        "url": "https://auto-screenshots.s3.us-west-2.amazonaws.com",
        "bucket": "auto-screenshots",
        "region": "us-west-2",
        "status": 200,
        "access": "public",
        "timestamp": "2026-01-16T21:09:52.495814"
      },
      {
        "url": "https://teste-auto.s3.us-east-1.amazonaws.com",
        "bucket": "teste-auto",
        "region": "us-east-1",
        "status": 200,
        "access": "public",
        "timestamp": "2026-01-16T21:11:19.608771"
      },
      {
        "url": "https://autotest.s3.us-east-1.amazonaws.com",
        "bucket": "autotest",
        "region": "us-east-1",
        "status": 200,
        "access": "public",
        "timestamp": "2026-01-16T21:15:06.102628"
      },
      {
        "url": "https://devauto.s3.us-east-1.amazonaws.com",
        "bucket": "devauto",
        "region": "us-east-1",
        "status": 200,
        "access": "public",
        "timestamp": "2026-01-16T21:28:34.822195"
      },
      {
        "url": "https://autocoding.s3.us-east-1.amazonaws.com",
        "bucket": "autocoding",
        "region": "us-east-1",
        "status": 200,
        "access": "public",
        "timestamp": "2026-01-16T21:35:26.228198"
      },
      {
        "url": "https://autopro.s3.ap-south-1.amazonaws.com",
        "bucket": "autopro",
        "region": "ap-south-1",
        "status": 200,
        "access": "public",
        "timestamp": "2026-01-16T21:42:22.853389"
      },
      {
        "url": "https://fxauto.s3.us-east-1.amazonaws.com",
        "bucket": "fxauto",
        "region": "us-east-1",
        "status": 200,
        "access": "public",
        "timestamp": "2026-01-16T21:42:24.243587"
      },
      {
        "url": "https://cloudauto.s3.ap-southeast-2.amazonaws.com",
        "bucket": "cloudauto",
        "region": "ap-southeast-2",
        "status": 200,
        "access": "public",
        "timestamp": "2026-01-16T21:44:59.228468"
      },
      {
        "url": "https://auto-portal.s3.us-east-2.amazonaws.com",
        "bucket": "auto-portal",
        "region": "us-east-2",
        "status": 200,
        "access": "public",
        "timestamp": "2026-01-16T21:46:08.430024"
      },
      {
        "url": "https://autoupload.s3.us-east-1.amazonaws.com",
        "bucket": "autoupload",
        "region": "us-east-1",
        "status": 200,
        "access": "public",
        "timestamp": "2026-01-16T21:58:27.305937"
      },
      {
        "url": "https://autoaction.s3.us-east-1.amazonaws.com",
        "bucket": "autoaction",
        "region": "us-east-1",
        "status": 200,
        "access": "public",
        "timestamp": "2026-01-16T22:11:21.253648"
      },
      {
        "url": "https://autopt.s3.eu-central-1.amazonaws.com",
        "bucket": "autopt",
        "region": "eu-central-1",
        "status": 200,
        "access": "public",
        "timestamp": "2026-01-16T22:17:32.788103"
      },
      {
        "url": "https://awsauto.s3.us-east-1.amazonaws.com",
        "bucket": "awsauto",
        "region": "us-east-1",
        "status": 200,
        "access": "public",
        "timestamp": "2026-01-16T22:18:20.198805"
      },
      {
        "url": "https://auto-review.s3.eu-west-1.amazonaws.com",
        "bucket": "auto-review",
        "region": "eu-west-1",
        "status": 200,
        "access": "public",
        "timestamp": "2026-01-16T22:18:52.057314"
      }
    ],
    "private": []
  },
  "stats": {
    "total_checked": 361323,
    "public_found": 39,
    "private_found": 0
  }
}