{
  "chunk_id": 1,
  "domain": "Simple",
  "date": "2026-01-22",
  "timestamp": "2026-01-22T17:07:21.345503",
  "providers": [
    "azure",
    "linode",
    "ibm",
    "digitalocean"
  ],
  "results": {
    "public": [
      {
        "url": "https://simple.ams3.digitaloceanspaces.com",
        "bucket": "simple",
        "provider": "digitalocean",
        "region": "ams3",
        "status": 200,
        "access": "public",
        "timestamp": "2026-01-22T16:31:13.921401"
      },
      {
        "url": "https://simplepos.sfo2.digitaloceanspaces.com",
        "bucket": "simplepos",
        "provider": "digitalocean",
        "region": "sfo2",
        "status": 200,
        "access": "public",
        "timestamp": "2026-01-22T16:55:56.497050"
      }
    ],
    "private": []
  },
  "stats": {
    "total_checked": 570510,
    "public_found": 2,
    "private_found": 0
  }
}