{
  "chunk_id": 1,
  "domain": "cisco",
  "date": "2026-03-03",
  "timestamp": "2026-03-03T07:50:53.836335",
  "results": {
    "public": [
      {
        "url": "https://1cisco.s3.us-east-1.amazonaws.com",
        "bucket": "1cisco",
        "region": "us-east-1",
        "status": 200,
        "access": "public",
        "timestamp": "2026-03-03T04:51:02.736789"
      },
      {
        "url": "https://cisco-publications.s3.us-east-1.amazonaws.com",
        "bucket": "cisco-publications",
        "region": "us-east-1",
        "status": 200,
        "access": "public",
        "timestamp": "2026-03-03T06:12:04.177502"
      },
      {
        "url": "https://cisco-emails.s3.us-east-1.amazonaws.com",
        "bucket": "cisco-emails",
        "region": "us-east-1",
        "status": 200,
        "access": "public",
        "timestamp": "2026-03-03T06:47:59.129775"
      },
      {
        "url": "https://cisco-demo.s3.us-east-1.amazonaws.com",
        "bucket": "cisco-demo",
        "region": "us-east-1",
        "status": 200,
        "access": "public",
        "timestamp": "2026-03-03T07:29:26.410146"
      }
    ],
    "private": []
  },
  "stats": {
    "total_checked": 361323,
    "public_found": 4,
    "private_found": 0
  }
}