{
  "chunk_id": 1,
  "domain": "coda",
  "date": "2026-03-11",
  "timestamp": "2026-03-11T14:47:06.093547",
  "results": {
    "public": [
      {
        "url": "https://codaavatars.s3.us-east-1.amazonaws.com",
        "bucket": "codaavatars",
        "region": "us-east-1",
        "status": 200,
        "access": "public",
        "timestamp": "2026-03-11T11:37:09.619977"
      },
      {
        "url": "https://coda-challenge.s3.ap-northeast-2.amazonaws.com",
        "bucket": "coda-challenge",
        "region": "ap-northeast-2",
        "status": 200,
        "access": "public",
        "timestamp": "2026-03-11T11:45:49.842036"
      },
      {
        "url": "https://arcoda.s3.us-east-1.amazonaws.com",
        "bucket": "arcoda",
        "region": "us-east-1",
        "status": 200,
        "access": "public",
        "timestamp": "2026-03-11T12:02:30.559853"
      },
      {
        "url": "https://codakit.s3.us-east-1.amazonaws.com",
        "bucket": "codakit",
        "region": "us-east-1",
        "status": 200,
        "access": "public",
        "timestamp": "2026-03-11T12:41:33.924683"
      },
      {
        "url": "https://coda-files.s3.us-west-2.amazonaws.com",
        "bucket": "coda-files",
        "region": "us-west-2",
        "status": 200,
        "access": "public",
        "timestamp": "2026-03-11T13:09:19.854893"
      },
      {
        "url": "https://sitecoda.s3.sa-east-1.amazonaws.com",
        "bucket": "sitecoda",
        "region": "sa-east-1",
        "status": 200,
        "access": "public",
        "timestamp": "2026-03-11T13:24:32.350958"
      }
    ],
    "private": []
  },
  "stats": {
    "total_checked": 361323,
    "public_found": 6,
    "private_found": 0
  }
}